{
  "/_not-found/page": "app/_not-found/page.js",
  "/api/accounts/[id]/route": "app/api/accounts/[id]/route.js",
  "/api/analytics/route": "app/api/analytics/route.js",
  "/api/accounts/route": "app/api/accounts/route.js",
  "/api/events/route": "app/api/events/route.js",
  "/api/health/route": "app/api/health/route.js",
  "/api/published/route": "app/api/published/route.js",
  "/api/queue/route": "app/api/queue/route.js",
  "/api/cron/every-15-min/route": "app/api/cron/every-15-min/route.js",
  "/page": "app/page.js",
  "/dashboard/analytics/page": "app/dashboard/analytics/page.js",
  "/dashboard/published/page": "app/dashboard/published/page.js",
  "/dashboard/queue/page": "app/dashboard/queue/page.js",
  "/dashboard/page": "app/dashboard/page.js",
  "/dashboard/sources/page": "app/dashboard/sources/page.js",
  "/dashboard/accounts/page": "app/dashboard/accounts/page.js"
}